UpFileLive/__init__.py
UpFileLive/upfilelive.py
upfilelive-1.0.6.dist-info/LICENSE
upfilelive-1.0.6.dist-info/METADATA
upfilelive-1.0.6.dist-info/WHEEL
upfilelive-1.0.6.dist-info/top_level.txt
upfilelive-1.0.6.dist-info/RECORD
