Metadata-Version: 2.2
Name: UpFileLive
Version: 1.0.6
Summary: A Python tool for interacting with upfile.live for file sharing.
Home-page: https://github.com/N791/UpFileLive
Author: MoeN791
Author-email: a15345506127@gmail.com
License: MIT
Classifier: Programming Language :: Python :: 3
Classifier: License :: OSI Approved :: MIT License
Requires-Python: >=3.7
License-File: LICENSE
Requires-Dist: playwright
Requires-Dist: loguru
Dynamic: author
Dynamic: author-email
Dynamic: classifier
Dynamic: home-page
Dynamic: license
Dynamic: requires-dist
Dynamic: requires-python
Dynamic: summary
